LICENSE.txt
MANIFEST.in
README.rst
setup.cfg
setup.py
django_thema.egg-info/PKG-INFO
django_thema.egg-info/SOURCES.txt
django_thema.egg-info/dependency_links.txt
django_thema.egg-info/not-zip-safe
django_thema.egg-info/requires.txt
django_thema.egg-info/top_level.txt
thema/__init__.py
thema/admin.py
thema/apps.py
thema/models.py
thema/data/Thema_v1.2.8_da.xlsx
thema/data/Thema_v1.2.8_de.xlsx
thema/data/Thema_v1.2.8_en.xlsx
thema/data/Thema_v1.2.8_es.xlsx
thema/data/Thema_v1.2.8_fr.xlsx
thema/data/Thema_v1.2.8_hu.xlsx
thema/data/Thema_v1.2.8_it.xlsx
thema/data/Thema_v1.2.8_ja.xlsx
thema/data/Thema_v1.2.8_lt.xlsx
thema/data/Thema_v1.2.8_nb.xlsx
thema/data/Thema_v1.2.8_pl.xlsx
thema/data/Thema_v1.2.8_pt.xlsx
thema/data/Thema_v1.2.8_sv.xlsx
thema/data/Thema_v1.2.8_tr.xlsx
thema/data/Thema_v1.2_ar.xlsx
thema/data/thema_ar.json
thema/data/thema_da.json
thema/data/thema_de.json
thema/data/thema_en.json
thema/data/thema_es.json
thema/data/thema_fr.json
thema/data/thema_hu.json
thema/data/thema_it.json
thema/data/thema_ja.json
thema/data/thema_lt.json
thema/data/thema_nb.json
thema/data/thema_pl.json
thema/data/thema_pt.json
thema/data/thema_sv.json
thema/data/thema_tr.json
thema/locale/ar/LC_MESSAGES/django.mo
thema/locale/ar/LC_MESSAGES/django.po
thema/locale/da/LC_MESSAGES/django.mo
thema/locale/da/LC_MESSAGES/django.po
thema/locale/de/LC_MESSAGES/django.mo
thema/locale/de/LC_MESSAGES/django.po
thema/locale/en/LC_MESSAGES/django.mo
thema/locale/en/LC_MESSAGES/django.po
thema/locale/es/LC_MESSAGES/django.mo
thema/locale/es/LC_MESSAGES/django.po
thema/locale/fr/LC_MESSAGES/django.mo
thema/locale/fr/LC_MESSAGES/django.po
thema/locale/hu/LC_MESSAGES/django.mo
thema/locale/hu/LC_MESSAGES/django.po
thema/locale/it/LC_MESSAGES/django.mo
thema/locale/it/LC_MESSAGES/django.po
thema/locale/ja/LC_MESSAGES/django.mo
thema/locale/ja/LC_MESSAGES/django.po
thema/locale/lt/LC_MESSAGES/django.mo
thema/locale/lt/LC_MESSAGES/django.po
thema/locale/nb/LC_MESSAGES/django.mo
thema/locale/nb/LC_MESSAGES/django.po
thema/locale/pl/LC_MESSAGES/django.mo
thema/locale/pl/LC_MESSAGES/django.po
thema/locale/pt/LC_MESSAGES/django.mo
thema/locale/pt/LC_MESSAGES/django.po
thema/locale/sv/LC_MESSAGES/django.mo
