Metadata-Version: 1.1
Name: django-thema
Version: 1.2.8
Summary: Application that provides EDItEUR Thema categories, and translations for the headers.
Home-page: https://saxo.githost.io/publish/django-thema
Author: Saxo Publish
Author-email: publish@saxo.com
License: BSD License 2.0
Keywords: django,thema,EDItEUR
Platform: UNKNOWN
Classifier: Framework :: Django
Classifier: Intended Audience :: Developers
Classifier: Programming Language :: Python :: 2
Classifier: Programming Language :: Python :: 3
